slackbot/__init__.py
slackbot/slackbot.py
simple_slackbot-0.1.0.dist-info/LICENSE
simple_slackbot-0.1.0.dist-info/METADATA
simple_slackbot-0.1.0.dist-info/WHEEL
simple_slackbot-0.1.0.dist-info/top_level.txt
simple_slackbot-0.1.0.dist-info/RECORD
