Metadata-Version: 2.1
Name: simple-slackbot
Version: 0.1.0
Summary: A simple python wrapper for the slack API
Home-page: https://github.com/chrisg1622/slackbot
Author: Chris George
Author-email: chrisg1622@gmail.com
License: UNKNOWN
Platform: UNKNOWN
Classifier: Programming Language :: Python :: 3
Classifier: License :: OSI Approved :: GNU General Public License (GPL)
Classifier: Operating System :: OS Independent
